ryetest/__init__.py
ryetest/__main__.py
ryetest/cli.py
ryetest-0.8.0.dist-info/METADATA
ryetest-0.8.0.dist-info/WHEEL
ryetest-0.8.0.dist-info/entry_points.txt
ryetest-0.8.0.dist-info/RECORD
